{
  "TemplatesPath": "..\\..\\..\\Projects\\StaticGenerics\\Templates",
  "Template": "Collections.List.TMPL.pas",
  "TCollectionsName": "TStudyCollections",
  "types": [
    {
      "type": "TRec_1_1",
      "type_flat": "TRec_1_1"
    },
    {
      "type": "TRec_1_2",
      "type_flat": "TRec_1_2"
    },
    {
      "type": "TRec_1_3",
      "type_flat": "TRec_1_3"
    },
    {
      "type": "TRec_1_4",
      "type_flat": "TRec_1_4"
    },
    {
      "type": "TRec_1_5",
      "type_flat": "TRec_1_5"
    },
    {
      "type": "TRec_1_6",
      "type_flat": "TRec_1_6"
    },
    {
      "type": "TRec_1_7",
      "type_flat": "TRec_1_7"
    },
    {
      "type": "TRec_1_8",
      "type_flat": "TRec_1_8"
    },
    {
      "type": "TRec_1_9",
      "type_flat": "TRec_1_9"
    },
    {
      "type": "TRec_1_10",
      "type_flat": "TRec_1_10"
    },
    {
      "type": "TRec_2_1",
      "type_flat": "TRec_2_1"
    },
    {
      "type": "TRec_2_2",
      "type_flat": "TRec_2_2"
    },
    {
      "type": "TRec_2_3",
      "type_flat": "TRec_2_3"
    },
    {
      "type": "TRec_2_4",
      "type_flat": "TRec_2_4"
    },
    {
      "type": "TRec_2_5",
      "type_flat": "TRec_2_5"
    },
    {
      "type": "TRec_2_6",
      "type_flat": "TRec_2_6"
    },
    {
      "type": "TRec_2_7",
      "type_flat": "TRec_2_7"
    },
    {
      "type": "TRec_2_8",
      "type_flat": "TRec_2_8"
    },
    {
      "type": "TRec_2_9",
      "type_flat": "TRec_2_9"
    },
    {
      "type": "TRec_2_10",
      "type_flat": "TRec_2_10"
    },
    {
      "type": "TRec_3_1",
      "type_flat": "TRec_3_1"
    },
    {
      "type": "TRec_3_2",
      "type_flat": "TRec_3_2"
    },
    {
      "type": "TRec_3_3",
      "type_flat": "TRec_3_3"
    },
    {
      "type": "TRec_3_4",
      "type_flat": "TRec_3_4"
    },
    {
      "type": "TRec_3_5",
      "type_flat": "TRec_3_5"
    },
    {
      "type": "TRec_3_6",
      "type_flat": "TRec_3_6"
    },
    {
      "type": "TRec_3_7",
      "type_flat": "TRec_3_7"
    },
    {
      "type": "TRec_3_8",
      "type_flat": "TRec_3_8"
    },
    {
      "type": "TRec_3_9",
      "type_flat": "TRec_3_9"
    },
    {
      "type": "TRec_3_10",
      "type_flat": "TRec_3_10"
    },
    {
      "type": "TRec_4_1",
      "type_flat": "TRec_4_1"
    },
    {
      "type": "TRec_4_2",
      "type_flat": "TRec_4_2"
    },
    {
      "type": "TRec_4_3",
      "type_flat": "TRec_4_3"
    },
    {
      "type": "TRec_4_4",
      "type_flat": "TRec_4_4"
    },
    {
      "type": "TRec_4_5",
      "type_flat": "TRec_4_5"
    },
    {
      "type": "TRec_4_6",
      "type_flat": "TRec_4_6"
    },
    {
      "type": "TRec_4_7",
      "type_flat": "TRec_4_7"
    },
    {
      "type": "TRec_4_8",
      "type_flat": "TRec_4_8"
    },
    {
      "type": "TRec_4_9",
      "type_flat": "TRec_4_9"
    },
    {
      "type": "TRec_4_10",
      "type_flat": "TRec_4_10"
    },
    {
      "type": "TRec_5_1",
      "type_flat": "TRec_5_1"
    },
    {
      "type": "TRec_5_2",
      "type_flat": "TRec_5_2"
    },
    {
      "type": "TRec_5_3",
      "type_flat": "TRec_5_3"
    },
    {
      "type": "TRec_5_4",
      "type_flat": "TRec_5_4"
    },
    {
      "type": "TRec_5_5",
      "type_flat": "TRec_5_5"
    },
    {
      "type": "TRec_5_6",
      "type_flat": "TRec_5_6"
    },
    {
      "type": "TRec_5_7",
      "type_flat": "TRec_5_7"
    },
    {
      "type": "TRec_5_8",
      "type_flat": "TRec_5_8"
    },
    {
      "type": "TRec_5_9",
      "type_flat": "TRec_5_9"
    },
    {
      "type": "TRec_5_10",
      "type_flat": "TRec_5_10"
    },
    {
      "type": "TRec_6_1",
      "type_flat": "TRec_6_1"
    },
    {
      "type": "TRec_6_2",
      "type_flat": "TRec_6_2"
    },
    {
      "type": "TRec_6_3",
      "type_flat": "TRec_6_3"
    },
    {
      "type": "TRec_6_4",
      "type_flat": "TRec_6_4"
    },
    {
      "type": "TRec_6_5",
      "type_flat": "TRec_6_5"
    },
    {
      "type": "TRec_6_6",
      "type_flat": "TRec_6_6"
    },
    {
      "type": "TRec_6_7",
      "type_flat": "TRec_6_7"
    },
    {
      "type": "TRec_6_8",
      "type_flat": "TRec_6_8"
    },
    {
      "type": "TRec_6_9",
      "type_flat": "TRec_6_9"
    },
    {
      "type": "TRec_6_10",
      "type_flat": "TRec_6_10"
    },
    {
      "type": "TRec_7_1",
      "type_flat": "TRec_7_1"
    },
    {
      "type": "TRec_7_2",
      "type_flat": "TRec_7_2"
    },
    {
      "type": "TRec_7_3",
      "type_flat": "TRec_7_3"
    },
    {
      "type": "TRec_7_4",
      "type_flat": "TRec_7_4"
    },
    {
      "type": "TRec_7_5",
      "type_flat": "TRec_7_5"
    },
    {
      "type": "TRec_7_6",
      "type_flat": "TRec_7_6"
    },
    {
      "type": "TRec_7_7",
      "type_flat": "TRec_7_7"
    },
    {
      "type": "TRec_7_8",
      "type_flat": "TRec_7_8"
    },
    {
      "type": "TRec_7_9",
      "type_flat": "TRec_7_9"
    },
    {
      "type": "TRec_7_10",
      "type_flat": "TRec_7_10"
    },
    {
      "type": "TRec_8_1",
      "type_flat": "TRec_8_1"
    },
    {
      "type": "TRec_8_2",
      "type_flat": "TRec_8_2"
    },
    {
      "type": "TRec_8_3",
      "type_flat": "TRec_8_3"
    },
    {
      "type": "TRec_8_4",
      "type_flat": "TRec_8_4"
    },
    {
      "type": "TRec_8_5",
      "type_flat": "TRec_8_5"
    },
    {
      "type": "TRec_8_6",
      "type_flat": "TRec_8_6"
    },
    {
      "type": "TRec_8_7",
      "type_flat": "TRec_8_7"
    },
    {
      "type": "TRec_8_8",
      "type_flat": "TRec_8_8"
    },
    {
      "type": "TRec_8_9",
      "type_flat": "TRec_8_9"
    },
    {
      "type": "TRec_8_10",
      "type_flat": "TRec_8_10"
    },
    {
      "type": "TRec_9_1",
      "type_flat": "TRec_9_1"
    },
    {
      "type": "TRec_9_2",
      "type_flat": "TRec_9_2"
    },
    {
      "type": "TRec_9_3",
      "type_flat": "TRec_9_3"
    },
    {
      "type": "TRec_9_4",
      "type_flat": "TRec_9_4"
    },
    {
      "type": "TRec_9_5",
      "type_flat": "TRec_9_5"
    },
    {
      "type": "TRec_9_6",
      "type_flat": "TRec_9_6"
    },
    {
      "type": "TRec_9_7",
      "type_flat": "TRec_9_7"
    },
    {
      "type": "TRec_9_8",
      "type_flat": "TRec_9_8"
    },
    {
      "type": "TRec_9_9",
      "type_flat": "TRec_9_9"
    },
    {
      "type": "TRec_9_10",
      "type_flat": "TRec_9_10"
    },
    {
      "type": "TRec_10_1",
      "type_flat": "TRec_10_1"
    },
    {
      "type": "TRec_10_2",
      "type_flat": "TRec_10_2"
    },
    {
      "type": "TRec_10_3",
      "type_flat": "TRec_10_3"
    },
    {
      "type": "TRec_10_4",
      "type_flat": "TRec_10_4"
    },
    {
      "type": "TRec_10_5",
      "type_flat": "TRec_10_5"
    },
    {
      "type": "TRec_10_6",
      "type_flat": "TRec_10_6"
    },
    {
      "type": "TRec_10_7",
      "type_flat": "TRec_10_7"
    },
    {
      "type": "TRec_10_8",
      "type_flat": "TRec_10_8"
    },
    {
      "type": "TRec_10_9",
      "type_flat": "TRec_10_9"
    },
    {
      "type": "TRec_10_10",
      "type_flat": "TRec_10_10"
    },
    {
      "type": "TRec_11_1",
      "type_flat": "TRec_11_1"
    },
    {
      "type": "TRec_11_2",
      "type_flat": "TRec_11_2"
    },
    {
      "type": "TRec_11_3",
      "type_flat": "TRec_11_3"
    },
    {
      "type": "TRec_11_4",
      "type_flat": "TRec_11_4"
    },
    {
      "type": "TRec_11_5",
      "type_flat": "TRec_11_5"
    },
    {
      "type": "TRec_11_6",
      "type_flat": "TRec_11_6"
    },
    {
      "type": "TRec_11_7",
      "type_flat": "TRec_11_7"
    },
    {
      "type": "TRec_11_8",
      "type_flat": "TRec_11_8"
    },
    {
      "type": "TRec_11_9",
      "type_flat": "TRec_11_9"
    },
    {
      "type": "TRec_11_10",
      "type_flat": "TRec_11_10"
    },
    {
      "type": "TRec_12_1",
      "type_flat": "TRec_12_1"
    },
    {
      "type": "TRec_12_2",
      "type_flat": "TRec_12_2"
    },
    {
      "type": "TRec_12_3",
      "type_flat": "TRec_12_3"
    },
    {
      "type": "TRec_12_4",
      "type_flat": "TRec_12_4"
    },
    {
      "type": "TRec_12_5",
      "type_flat": "TRec_12_5"
    },
    {
      "type": "TRec_12_6",
      "type_flat": "TRec_12_6"
    },
    {
      "type": "TRec_12_7",
      "type_flat": "TRec_12_7"
    },
    {
      "type": "TRec_12_8",
      "type_flat": "TRec_12_8"
    },
    {
      "type": "TRec_12_9",
      "type_flat": "TRec_12_9"
    },
    {
      "type": "TRec_12_10",
      "type_flat": "TRec_12_10"
    },
    {
      "type": "TRec_13_1",
      "type_flat": "TRec_13_1"
    },
    {
      "type": "TRec_13_2",
      "type_flat": "TRec_13_2"
    },
    {
      "type": "TRec_13_3",
      "type_flat": "TRec_13_3"
    },
    {
      "type": "TRec_13_4",
      "type_flat": "TRec_13_4"
    },
    {
      "type": "TRec_13_5",
      "type_flat": "TRec_13_5"
    },
    {
      "type": "TRec_13_6",
      "type_flat": "TRec_13_6"
    },
    {
      "type": "TRec_13_7",
      "type_flat": "TRec_13_7"
    },
    {
      "type": "TRec_13_8",
      "type_flat": "TRec_13_8"
    },
    {
      "type": "TRec_13_9",
      "type_flat": "TRec_13_9"
    },
    {
      "type": "TRec_13_10",
      "type_flat": "TRec_13_10"
    },
    {
      "type": "TRec_14_1",
      "type_flat": "TRec_14_1"
    },
    {
      "type": "TRec_14_2",
      "type_flat": "TRec_14_2"
    },
    {
      "type": "TRec_14_3",
      "type_flat": "TRec_14_3"
    },
    {
      "type": "TRec_14_4",
      "type_flat": "TRec_14_4"
    },
    {
      "type": "TRec_14_5",
      "type_flat": "TRec_14_5"
    },
    {
      "type": "TRec_14_6",
      "type_flat": "TRec_14_6"
    },
    {
      "type": "TRec_14_7",
      "type_flat": "TRec_14_7"
    },
    {
      "type": "TRec_14_8",
      "type_flat": "TRec_14_8"
    },
    {
      "type": "TRec_14_9",
      "type_flat": "TRec_14_9"
    },
    {
      "type": "TRec_14_10",
      "type_flat": "TRec_14_10"
    },
    {
      "type": "TRec_15_1",
      "type_flat": "TRec_15_1"
    },
    {
      "type": "TRec_15_2",
      "type_flat": "TRec_15_2"
    },
    {
      "type": "TRec_15_3",
      "type_flat": "TRec_15_3"
    },
    {
      "type": "TRec_15_4",
      "type_flat": "TRec_15_4"
    },
    {
      "type": "TRec_15_5",
      "type_flat": "TRec_15_5"
    },
    {
      "type": "TRec_15_6",
      "type_flat": "TRec_15_6"
    },
    {
      "type": "TRec_15_7",
      "type_flat": "TRec_15_7"
    },
    {
      "type": "TRec_15_8",
      "type_flat": "TRec_15_8"
    },
    {
      "type": "TRec_15_9",
      "type_flat": "TRec_15_9"
    },
    {
      "type": "TRec_15_10",
      "type_flat": "TRec_15_10"
    },
    {
      "type": "TRec_16_1",
      "type_flat": "TRec_16_1"
    },
    {
      "type": "TRec_16_2",
      "type_flat": "TRec_16_2"
    },
    {
      "type": "TRec_16_3",
      "type_flat": "TRec_16_3"
    },
    {
      "type": "TRec_16_4",
      "type_flat": "TRec_16_4"
    },
    {
      "type": "TRec_16_5",
      "type_flat": "TRec_16_5"
    },
    {
      "type": "TRec_16_6",
      "type_flat": "TRec_16_6"
    },
    {
      "type": "TRec_16_7",
      "type_flat": "TRec_16_7"
    },
    {
      "type": "TRec_16_8",
      "type_flat": "TRec_16_8"
    },
    {
      "type": "TRec_16_9",
      "type_flat": "TRec_16_9"
    },
    {
      "type": "TRec_16_10",
      "type_flat": "TRec_16_10"
    },
    {
      "type": "TRec_17_1",
      "type_flat": "TRec_17_1"
    },
    {
      "type": "TRec_17_2",
      "type_flat": "TRec_17_2"
    },
    {
      "type": "TRec_17_3",
      "type_flat": "TRec_17_3"
    },
    {
      "type": "TRec_17_4",
      "type_flat": "TRec_17_4"
    },
    {
      "type": "TRec_17_5",
      "type_flat": "TRec_17_5"
    },
    {
      "type": "TRec_17_6",
      "type_flat": "TRec_17_6"
    },
    {
      "type": "TRec_17_7",
      "type_flat": "TRec_17_7"
    },
    {
      "type": "TRec_17_8",
      "type_flat": "TRec_17_8"
    },
    {
      "type": "TRec_17_9",
      "type_flat": "TRec_17_9"
    },
    {
      "type": "TRec_17_10",
      "type_flat": "TRec_17_10"
    },
    {
      "type": "TRec_18_1",
      "type_flat": "TRec_18_1"
    },
    {
      "type": "TRec_18_2",
      "type_flat": "TRec_18_2"
    },
    {
      "type": "TRec_18_3",
      "type_flat": "TRec_18_3"
    },
    {
      "type": "TRec_18_4",
      "type_flat": "TRec_18_4"
    },
    {
      "type": "TRec_18_5",
      "type_flat": "TRec_18_5"
    },
    {
      "type": "TRec_18_6",
      "type_flat": "TRec_18_6"
    },
    {
      "type": "TRec_18_7",
      "type_flat": "TRec_18_7"
    },
    {
      "type": "TRec_18_8",
      "type_flat": "TRec_18_8"
    },
    {
      "type": "TRec_18_9",
      "type_flat": "TRec_18_9"
    },
    {
      "type": "TRec_18_10",
      "type_flat": "TRec_18_10"
    },
    {
      "type": "TRec_19_1",
      "type_flat": "TRec_19_1"
    },
    {
      "type": "TRec_19_2",
      "type_flat": "TRec_19_2"
    },
    {
      "type": "TRec_19_3",
      "type_flat": "TRec_19_3"
    },
    {
      "type": "TRec_19_4",
      "type_flat": "TRec_19_4"
    },
    {
      "type": "TRec_19_5",
      "type_flat": "TRec_19_5"
    },
    {
      "type": "TRec_19_6",
      "type_flat": "TRec_19_6"
    },
    {
      "type": "TRec_19_7",
      "type_flat": "TRec_19_7"
    },
    {
      "type": "TRec_19_8",
      "type_flat": "TRec_19_8"
    },
    {
      "type": "TRec_19_9",
      "type_flat": "TRec_19_9"
    },
    {
      "type": "TRec_19_10",
      "type_flat": "TRec_19_10"
    },
    {
      "type": "TRec_20_1",
      "type_flat": "TRec_20_1"
    },
    {
      "type": "TRec_20_2",
      "type_flat": "TRec_20_2"
    },
    {
      "type": "TRec_20_3",
      "type_flat": "TRec_20_3"
    },
    {
      "type": "TRec_20_4",
      "type_flat": "TRec_20_4"
    },
    {
      "type": "TRec_20_5",
      "type_flat": "TRec_20_5"
    },
    {
      "type": "TRec_20_6",
      "type_flat": "TRec_20_6"
    },
    {
      "type": "TRec_20_7",
      "type_flat": "TRec_20_7"
    },
    {
      "type": "TRec_20_8",
      "type_flat": "TRec_20_8"
    },
    {
      "type": "TRec_20_9",
      "type_flat": "TRec_20_9"
    },
    {
      "type": "TRec_20_10",
      "type_flat": "TRec_20_10"
    },
    {
      "type": "TRec_21_1",
      "type_flat": "TRec_21_1"
    },
    {
      "type": "TRec_21_2",
      "type_flat": "TRec_21_2"
    },
    {
      "type": "TRec_21_3",
      "type_flat": "TRec_21_3"
    },
    {
      "type": "TRec_21_4",
      "type_flat": "TRec_21_4"
    },
    {
      "type": "TRec_21_5",
      "type_flat": "TRec_21_5"
    },
    {
      "type": "TRec_21_6",
      "type_flat": "TRec_21_6"
    },
    {
      "type": "TRec_21_7",
      "type_flat": "TRec_21_7"
    },
    {
      "type": "TRec_21_8",
      "type_flat": "TRec_21_8"
    },
    {
      "type": "TRec_21_9",
      "type_flat": "TRec_21_9"
    },
    {
      "type": "TRec_21_10",
      "type_flat": "TRec_21_10"
    },
    {
      "type": "TRec_22_1",
      "type_flat": "TRec_22_1"
    },
    {
      "type": "TRec_22_2",
      "type_flat": "TRec_22_2"
    },
    {
      "type": "TRec_22_3",
      "type_flat": "TRec_22_3"
    },
    {
      "type": "TRec_22_4",
      "type_flat": "TRec_22_4"
    },
    {
      "type": "TRec_22_5",
      "type_flat": "TRec_22_5"
    },
    {
      "type": "TRec_22_6",
      "type_flat": "TRec_22_6"
    },
    {
      "type": "TRec_22_7",
      "type_flat": "TRec_22_7"
    },
    {
      "type": "TRec_22_8",
      "type_flat": "TRec_22_8"
    },
    {
      "type": "TRec_22_9",
      "type_flat": "TRec_22_9"
    },
    {
      "type": "TRec_22_10",
      "type_flat": "TRec_22_10"
    },
    {
      "type": "TRec_23_1",
      "type_flat": "TRec_23_1"
    },
    {
      "type": "TRec_23_2",
      "type_flat": "TRec_23_2"
    },
    {
      "type": "TRec_23_3",
      "type_flat": "TRec_23_3"
    },
    {
      "type": "TRec_23_4",
      "type_flat": "TRec_23_4"
    },
    {
      "type": "TRec_23_5",
      "type_flat": "TRec_23_5"
    },
    {
      "type": "TRec_23_6",
      "type_flat": "TRec_23_6"
    },
    {
      "type": "TRec_23_7",
      "type_flat": "TRec_23_7"
    },
    {
      "type": "TRec_23_8",
      "type_flat": "TRec_23_8"
    },
    {
      "type": "TRec_23_9",
      "type_flat": "TRec_23_9"
    },
    {
      "type": "TRec_23_10",
      "type_flat": "TRec_23_10"
    },
    {
      "type": "TRec_24_1",
      "type_flat": "TRec_24_1"
    },
    {
      "type": "TRec_24_2",
      "type_flat": "TRec_24_2"
    },
    {
      "type": "TRec_24_3",
      "type_flat": "TRec_24_3"
    },
    {
      "type": "TRec_24_4",
      "type_flat": "TRec_24_4"
    },
    {
      "type": "TRec_24_5",
      "type_flat": "TRec_24_5"
    },
    {
      "type": "TRec_24_6",
      "type_flat": "TRec_24_6"
    },
    {
      "type": "TRec_24_7",
      "type_flat": "TRec_24_7"
    },
    {
      "type": "TRec_24_8",
      "type_flat": "TRec_24_8"
    },
    {
      "type": "TRec_24_9",
      "type_flat": "TRec_24_9"
    },
    {
      "type": "TRec_24_10",
      "type_flat": "TRec_24_10"
    },
    {
      "type": "TRec_25_1",
      "type_flat": "TRec_25_1"
    },
    {
      "type": "TRec_25_2",
      "type_flat": "TRec_25_2"
    },
    {
      "type": "TRec_25_3",
      "type_flat": "TRec_25_3"
    },
    {
      "type": "TRec_25_4",
      "type_flat": "TRec_25_4"
    },
    {
      "type": "TRec_25_5",
      "type_flat": "TRec_25_5"
    },
    {
      "type": "TRec_25_6",
      "type_flat": "TRec_25_6"
    },
    {
      "type": "TRec_25_7",
      "type_flat": "TRec_25_7"
    },
    {
      "type": "TRec_25_8",
      "type_flat": "TRec_25_8"
    },
    {
      "type": "TRec_25_9",
      "type_flat": "TRec_25_9"
    },
    {
      "type": "TRec_25_10",
      "type_flat": "TRec_25_10"
    },
    {
      "type": "TRec_26_1",
      "type_flat": "TRec_26_1"
    },
    {
      "type": "TRec_26_2",
      "type_flat": "TRec_26_2"
    },
    {
      "type": "TRec_26_3",
      "type_flat": "TRec_26_3"
    },
    {
      "type": "TRec_26_4",
      "type_flat": "TRec_26_4"
    },
    {
      "type": "TRec_26_5",
      "type_flat": "TRec_26_5"
    },
    {
      "type": "TRec_26_6",
      "type_flat": "TRec_26_6"
    },
    {
      "type": "TRec_26_7",
      "type_flat": "TRec_26_7"
    },
    {
      "type": "TRec_26_8",
      "type_flat": "TRec_26_8"
    },
    {
      "type": "TRec_26_9",
      "type_flat": "TRec_26_9"
    },
    {
      "type": "TRec_26_10",
      "type_flat": "TRec_26_10"
    },
    {
      "type": "TRec_27_1",
      "type_flat": "TRec_27_1"
    },
    {
      "type": "TRec_27_2",
      "type_flat": "TRec_27_2"
    },
    {
      "type": "TRec_27_3",
      "type_flat": "TRec_27_3"
    },
    {
      "type": "TRec_27_4",
      "type_flat": "TRec_27_4"
    },
    {
      "type": "TRec_27_5",
      "type_flat": "TRec_27_5"
    },
    {
      "type": "TRec_27_6",
      "type_flat": "TRec_27_6"
    },
    {
      "type": "TRec_27_7",
      "type_flat": "TRec_27_7"
    },
    {
      "type": "TRec_27_8",
      "type_flat": "TRec_27_8"
    },
    {
      "type": "TRec_27_9",
      "type_flat": "TRec_27_9"
    },
    {
      "type": "TRec_27_10",
      "type_flat": "TRec_27_10"
    },
    {
      "type": "TRec_28_1",
      "type_flat": "TRec_28_1"
    },
    {
      "type": "TRec_28_2",
      "type_flat": "TRec_28_2"
    },
    {
      "type": "TRec_28_3",
      "type_flat": "TRec_28_3"
    },
    {
      "type": "TRec_28_4",
      "type_flat": "TRec_28_4"
    },
    {
      "type": "TRec_28_5",
      "type_flat": "TRec_28_5"
    },
    {
      "type": "TRec_28_6",
      "type_flat": "TRec_28_6"
    },
    {
      "type": "TRec_28_7",
      "type_flat": "TRec_28_7"
    },
    {
      "type": "TRec_28_8",
      "type_flat": "TRec_28_8"
    },
    {
      "type": "TRec_28_9",
      "type_flat": "TRec_28_9"
    },
    {
      "type": "TRec_28_10",
      "type_flat": "TRec_28_10"
    },
    {
      "type": "TRec_29_1",
      "type_flat": "TRec_29_1"
    },
    {
      "type": "TRec_29_2",
      "type_flat": "TRec_29_2"
    },
    {
      "type": "TRec_29_3",
      "type_flat": "TRec_29_3"
    },
    {
      "type": "TRec_29_4",
      "type_flat": "TRec_29_4"
    },
    {
      "type": "TRec_29_5",
      "type_flat": "TRec_29_5"
    },
    {
      "type": "TRec_29_6",
      "type_flat": "TRec_29_6"
    },
    {
      "type": "TRec_29_7",
      "type_flat": "TRec_29_7"
    },
    {
      "type": "TRec_29_8",
      "type_flat": "TRec_29_8"
    },
    {
      "type": "TRec_29_9",
      "type_flat": "TRec_29_9"
    },
    {
      "type": "TRec_29_10",
      "type_flat": "TRec_29_10"
    },
    {
      "type": "TRec_30_1",
      "type_flat": "TRec_30_1"
    },
    {
      "type": "TRec_30_2",
      "type_flat": "TRec_30_2"
    },
    {
      "type": "TRec_30_3",
      "type_flat": "TRec_30_3"
    },
    {
      "type": "TRec_30_4",
      "type_flat": "TRec_30_4"
    },
    {
      "type": "TRec_30_5",
      "type_flat": "TRec_30_5"
    },
    {
      "type": "TRec_30_6",
      "type_flat": "TRec_30_6"
    },
    {
      "type": "TRec_30_7",
      "type_flat": "TRec_30_7"
    },
    {
      "type": "TRec_30_8",
      "type_flat": "TRec_30_8"
    },
    {
      "type": "TRec_30_9",
      "type_flat": "TRec_30_9"
    },
    {
      "type": "TRec_30_10",
      "type_flat": "TRec_30_10"
    },
    {
      "type": "TRec_31_1",
      "type_flat": "TRec_31_1"
    },
    {
      "type": "TRec_31_2",
      "type_flat": "TRec_31_2"
    },
    {
      "type": "TRec_31_3",
      "type_flat": "TRec_31_3"
    },
    {
      "type": "TRec_31_4",
      "type_flat": "TRec_31_4"
    },
    {
      "type": "TRec_31_5",
      "type_flat": "TRec_31_5"
    },
    {
      "type": "TRec_31_6",
      "type_flat": "TRec_31_6"
    },
    {
      "type": "TRec_31_7",
      "type_flat": "TRec_31_7"
    },
    {
      "type": "TRec_31_8",
      "type_flat": "TRec_31_8"
    },
    {
      "type": "TRec_31_9",
      "type_flat": "TRec_31_9"
    },
    {
      "type": "TRec_31_10",
      "type_flat": "TRec_31_10"
    },
    {
      "type": "TRec_32_1",
      "type_flat": "TRec_32_1"
    },
    {
      "type": "TRec_32_2",
      "type_flat": "TRec_32_2"
    },
    {
      "type": "TRec_32_3",
      "type_flat": "TRec_32_3"
    },
    {
      "type": "TRec_32_4",
      "type_flat": "TRec_32_4"
    },
    {
      "type": "TRec_32_5",
      "type_flat": "TRec_32_5"
    },
    {
      "type": "TRec_32_6",
      "type_flat": "TRec_32_6"
    },
    {
      "type": "TRec_32_7",
      "type_flat": "TRec_32_7"
    },
    {
      "type": "TRec_32_8",
      "type_flat": "TRec_32_8"
    },
    {
      "type": "TRec_32_9",
      "type_flat": "TRec_32_9"
    },
    {
      "type": "TRec_32_10",
      "type_flat": "TRec_32_10"
    },
    {
      "type": "TRec_33_1",
      "type_flat": "TRec_33_1"
    },
    {
      "type": "TRec_33_2",
      "type_flat": "TRec_33_2"
    },
    {
      "type": "TRec_33_3",
      "type_flat": "TRec_33_3"
    },
    {
      "type": "TRec_33_4",
      "type_flat": "TRec_33_4"
    },
    {
      "type": "TRec_33_5",
      "type_flat": "TRec_33_5"
    },
    {
      "type": "TRec_33_6",
      "type_flat": "TRec_33_6"
    },
    {
      "type": "TRec_33_7",
      "type_flat": "TRec_33_7"
    },
    {
      "type": "TRec_33_8",
      "type_flat": "TRec_33_8"
    },
    {
      "type": "TRec_33_9",
      "type_flat": "TRec_33_9"
    },
    {
      "type": "TRec_33_10",
      "type_flat": "TRec_33_10"
    },
    {
      "type": "TRec_34_1",
      "type_flat": "TRec_34_1"
    },
    {
      "type": "TRec_34_2",
      "type_flat": "TRec_34_2"
    },
    {
      "type": "TRec_34_3",
      "type_flat": "TRec_34_3"
    },
    {
      "type": "TRec_34_4",
      "type_flat": "TRec_34_4"
    },
    {
      "type": "TRec_34_5",
      "type_flat": "TRec_34_5"
    },
    {
      "type": "TRec_34_6",
      "type_flat": "TRec_34_6"
    },
    {
      "type": "TRec_34_7",
      "type_flat": "TRec_34_7"
    },
    {
      "type": "TRec_34_8",
      "type_flat": "TRec_34_8"
    },
    {
      "type": "TRec_34_9",
      "type_flat": "TRec_34_9"
    },
    {
      "type": "TRec_34_10",
      "type_flat": "TRec_34_10"
    },
    {
      "type": "TRec_35_1",
      "type_flat": "TRec_35_1"
    },
    {
      "type": "TRec_35_2",
      "type_flat": "TRec_35_2"
    },
    {
      "type": "TRec_35_3",
      "type_flat": "TRec_35_3"
    },
    {
      "type": "TRec_35_4",
      "type_flat": "TRec_35_4"
    },
    {
      "type": "TRec_35_5",
      "type_flat": "TRec_35_5"
    },
    {
      "type": "TRec_35_6",
      "type_flat": "TRec_35_6"
    },
    {
      "type": "TRec_35_7",
      "type_flat": "TRec_35_7"
    },
    {
      "type": "TRec_35_8",
      "type_flat": "TRec_35_8"
    },
    {
      "type": "TRec_35_9",
      "type_flat": "TRec_35_9"
    },
    {
      "type": "TRec_35_10",
      "type_flat": "TRec_35_10"
    },
    {
      "type": "TRec_36_1",
      "type_flat": "TRec_36_1"
    },
    {
      "type": "TRec_36_2",
      "type_flat": "TRec_36_2"
    },
    {
      "type": "TRec_36_3",
      "type_flat": "TRec_36_3"
    },
    {
      "type": "TRec_36_4",
      "type_flat": "TRec_36_4"
    },
    {
      "type": "TRec_36_5",
      "type_flat": "TRec_36_5"
    },
    {
      "type": "TRec_36_6",
      "type_flat": "TRec_36_6"
    },
    {
      "type": "TRec_36_7",
      "type_flat": "TRec_36_7"
    },
    {
      "type": "TRec_36_8",
      "type_flat": "TRec_36_8"
    },
    {
      "type": "TRec_36_9",
      "type_flat": "TRec_36_9"
    },
    {
      "type": "TRec_36_10",
      "type_flat": "TRec_36_10"
    },
    {
      "type": "TRec_37_1",
      "type_flat": "TRec_37_1"
    },
    {
      "type": "TRec_37_2",
      "type_flat": "TRec_37_2"
    },
    {
      "type": "TRec_37_3",
      "type_flat": "TRec_37_3"
    },
    {
      "type": "TRec_37_4",
      "type_flat": "TRec_37_4"
    },
    {
      "type": "TRec_37_5",
      "type_flat": "TRec_37_5"
    },
    {
      "type": "TRec_37_6",
      "type_flat": "TRec_37_6"
    },
    {
      "type": "TRec_37_7",
      "type_flat": "TRec_37_7"
    },
    {
      "type": "TRec_37_8",
      "type_flat": "TRec_37_8"
    },
    {
      "type": "TRec_37_9",
      "type_flat": "TRec_37_9"
    },
    {
      "type": "TRec_37_10",
      "type_flat": "TRec_37_10"
    },
    {
      "type": "TRec_38_1",
      "type_flat": "TRec_38_1"
    },
    {
      "type": "TRec_38_2",
      "type_flat": "TRec_38_2"
    },
    {
      "type": "TRec_38_3",
      "type_flat": "TRec_38_3"
    },
    {
      "type": "TRec_38_4",
      "type_flat": "TRec_38_4"
    },
    {
      "type": "TRec_38_5",
      "type_flat": "TRec_38_5"
    },
    {
      "type": "TRec_38_6",
      "type_flat": "TRec_38_6"
    },
    {
      "type": "TRec_38_7",
      "type_flat": "TRec_38_7"
    },
    {
      "type": "TRec_38_8",
      "type_flat": "TRec_38_8"
    },
    {
      "type": "TRec_38_9",
      "type_flat": "TRec_38_9"
    },
    {
      "type": "TRec_38_10",
      "type_flat": "TRec_38_10"
    },
    {
      "type": "TRec_39_1",
      "type_flat": "TRec_39_1"
    },
    {
      "type": "TRec_39_2",
      "type_flat": "TRec_39_2"
    },
    {
      "type": "TRec_39_3",
      "type_flat": "TRec_39_3"
    },
    {
      "type": "TRec_39_4",
      "type_flat": "TRec_39_4"
    },
    {
      "type": "TRec_39_5",
      "type_flat": "TRec_39_5"
    },
    {
      "type": "TRec_39_6",
      "type_flat": "TRec_39_6"
    },
    {
      "type": "TRec_39_7",
      "type_flat": "TRec_39_7"
    },
    {
      "type": "TRec_39_8",
      "type_flat": "TRec_39_8"
    },
    {
      "type": "TRec_39_9",
      "type_flat": "TRec_39_9"
    },
    {
      "type": "TRec_39_10",
      "type_flat": "TRec_39_10"
    },
    {
      "type": "TRec_40_1",
      "type_flat": "TRec_40_1"
    },
    {
      "type": "TRec_40_2",
      "type_flat": "TRec_40_2"
    },
    {
      "type": "TRec_40_3",
      "type_flat": "TRec_40_3"
    },
    {
      "type": "TRec_40_4",
      "type_flat": "TRec_40_4"
    },
    {
      "type": "TRec_40_5",
      "type_flat": "TRec_40_5"
    },
    {
      "type": "TRec_40_6",
      "type_flat": "TRec_40_6"
    },
    {
      "type": "TRec_40_7",
      "type_flat": "TRec_40_7"
    },
    {
      "type": "TRec_40_8",
      "type_flat": "TRec_40_8"
    },
    {
      "type": "TRec_40_9",
      "type_flat": "TRec_40_9"
    },
    {
      "type": "TRec_40_10",
      "type_flat": "TRec_40_10"
    },
    {
      "type": "TRec_41_1",
      "type_flat": "TRec_41_1"
    },
    {
      "type": "TRec_41_2",
      "type_flat": "TRec_41_2"
    },
    {
      "type": "TRec_41_3",
      "type_flat": "TRec_41_3"
    },
    {
      "type": "TRec_41_4",
      "type_flat": "TRec_41_4"
    },
    {
      "type": "TRec_41_5",
      "type_flat": "TRec_41_5"
    },
    {
      "type": "TRec_41_6",
      "type_flat": "TRec_41_6"
    },
    {
      "type": "TRec_41_7",
      "type_flat": "TRec_41_7"
    },
    {
      "type": "TRec_41_8",
      "type_flat": "TRec_41_8"
    },
    {
      "type": "TRec_41_9",
      "type_flat": "TRec_41_9"
    },
    {
      "type": "TRec_41_10",
      "type_flat": "TRec_41_10"
    },
    {
      "type": "TRec_42_1",
      "type_flat": "TRec_42_1"
    },
    {
      "type": "TRec_42_2",
      "type_flat": "TRec_42_2"
    },
    {
      "type": "TRec_42_3",
      "type_flat": "TRec_42_3"
    },
    {
      "type": "TRec_42_4",
      "type_flat": "TRec_42_4"
    },
    {
      "type": "TRec_42_5",
      "type_flat": "TRec_42_5"
    },
    {
      "type": "TRec_42_6",
      "type_flat": "TRec_42_6"
    },
    {
      "type": "TRec_42_7",
      "type_flat": "TRec_42_7"
    },
    {
      "type": "TRec_42_8",
      "type_flat": "TRec_42_8"
    },
    {
      "type": "TRec_42_9",
      "type_flat": "TRec_42_9"
    },
    {
      "type": "TRec_42_10",
      "type_flat": "TRec_42_10"
    },
    {
      "type": "TRec_43_1",
      "type_flat": "TRec_43_1"
    },
    {
      "type": "TRec_43_2",
      "type_flat": "TRec_43_2"
    },
    {
      "type": "TRec_43_3",
      "type_flat": "TRec_43_3"
    },
    {
      "type": "TRec_43_4",
      "type_flat": "TRec_43_4"
    },
    {
      "type": "TRec_43_5",
      "type_flat": "TRec_43_5"
    },
    {
      "type": "TRec_43_6",
      "type_flat": "TRec_43_6"
    },
    {
      "type": "TRec_43_7",
      "type_flat": "TRec_43_7"
    },
    {
      "type": "TRec_43_8",
      "type_flat": "TRec_43_8"
    },
    {
      "type": "TRec_43_9",
      "type_flat": "TRec_43_9"
    },
    {
      "type": "TRec_43_10",
      "type_flat": "TRec_43_10"
    },
    {
      "type": "TRec_44_1",
      "type_flat": "TRec_44_1"
    },
    {
      "type": "TRec_44_2",
      "type_flat": "TRec_44_2"
    },
    {
      "type": "TRec_44_3",
      "type_flat": "TRec_44_3"
    },
    {
      "type": "TRec_44_4",
      "type_flat": "TRec_44_4"
    },
    {
      "type": "TRec_44_5",
      "type_flat": "TRec_44_5"
    },
    {
      "type": "TRec_44_6",
      "type_flat": "TRec_44_6"
    },
    {
      "type": "TRec_44_7",
      "type_flat": "TRec_44_7"
    },
    {
      "type": "TRec_44_8",
      "type_flat": "TRec_44_8"
    },
    {
      "type": "TRec_44_9",
      "type_flat": "TRec_44_9"
    },
    {
      "type": "TRec_44_10",
      "type_flat": "TRec_44_10"
    },
    {
      "type": "TRec_45_1",
      "type_flat": "TRec_45_1"
    },
    {
      "type": "TRec_45_2",
      "type_flat": "TRec_45_2"
    },
    {
      "type": "TRec_45_3",
      "type_flat": "TRec_45_3"
    },
    {
      "type": "TRec_45_4",
      "type_flat": "TRec_45_4"
    },
    {
      "type": "TRec_45_5",
      "type_flat": "TRec_45_5"
    },
    {
      "type": "TRec_45_6",
      "type_flat": "TRec_45_6"
    },
    {
      "type": "TRec_45_7",
      "type_flat": "TRec_45_7"
    },
    {
      "type": "TRec_45_8",
      "type_flat": "TRec_45_8"
    },
    {
      "type": "TRec_45_9",
      "type_flat": "TRec_45_9"
    },
    {
      "type": "TRec_45_10",
      "type_flat": "TRec_45_10"
    },
    {
      "type": "TRec_46_1",
      "type_flat": "TRec_46_1"
    },
    {
      "type": "TRec_46_2",
      "type_flat": "TRec_46_2"
    },
    {
      "type": "TRec_46_3",
      "type_flat": "TRec_46_3"
    },
    {
      "type": "TRec_46_4",
      "type_flat": "TRec_46_4"
    },
    {
      "type": "TRec_46_5",
      "type_flat": "TRec_46_5"
    },
    {
      "type": "TRec_46_6",
      "type_flat": "TRec_46_6"
    },
    {
      "type": "TRec_46_7",
      "type_flat": "TRec_46_7"
    },
    {
      "type": "TRec_46_8",
      "type_flat": "TRec_46_8"
    },
    {
      "type": "TRec_46_9",
      "type_flat": "TRec_46_9"
    },
    {
      "type": "TRec_46_10",
      "type_flat": "TRec_46_10"
    },
    {
      "type": "TRec_47_1",
      "type_flat": "TRec_47_1"
    },
    {
      "type": "TRec_47_2",
      "type_flat": "TRec_47_2"
    },
    {
      "type": "TRec_47_3",
      "type_flat": "TRec_47_3"
    },
    {
      "type": "TRec_47_4",
      "type_flat": "TRec_47_4"
    },
    {
      "type": "TRec_47_5",
      "type_flat": "TRec_47_5"
    },
    {
      "type": "TRec_47_6",
      "type_flat": "TRec_47_6"
    },
    {
      "type": "TRec_47_7",
      "type_flat": "TRec_47_7"
    },
    {
      "type": "TRec_47_8",
      "type_flat": "TRec_47_8"
    },
    {
      "type": "TRec_47_9",
      "type_flat": "TRec_47_9"
    },
    {
      "type": "TRec_47_10",
      "type_flat": "TRec_47_10"
    },
    {
      "type": "TRec_48_1",
      "type_flat": "TRec_48_1"
    },
    {
      "type": "TRec_48_2",
      "type_flat": "TRec_48_2"
    },
    {
      "type": "TRec_48_3",
      "type_flat": "TRec_48_3"
    },
    {
      "type": "TRec_48_4",
      "type_flat": "TRec_48_4"
    },
    {
      "type": "TRec_48_5",
      "type_flat": "TRec_48_5"
    },
    {
      "type": "TRec_48_6",
      "type_flat": "TRec_48_6"
    },
    {
      "type": "TRec_48_7",
      "type_flat": "TRec_48_7"
    },
    {
      "type": "TRec_48_8",
      "type_flat": "TRec_48_8"
    },
    {
      "type": "TRec_48_9",
      "type_flat": "TRec_48_9"
    },
    {
      "type": "TRec_48_10",
      "type_flat": "TRec_48_10"
    },
    {
      "type": "TRec_49_1",
      "type_flat": "TRec_49_1"
    },
    {
      "type": "TRec_49_2",
      "type_flat": "TRec_49_2"
    },
    {
      "type": "TRec_49_3",
      "type_flat": "TRec_49_3"
    },
    {
      "type": "TRec_49_4",
      "type_flat": "TRec_49_4"
    },
    {
      "type": "TRec_49_5",
      "type_flat": "TRec_49_5"
    },
    {
      "type": "TRec_49_6",
      "type_flat": "TRec_49_6"
    },
    {
      "type": "TRec_49_7",
      "type_flat": "TRec_49_7"
    },
    {
      "type": "TRec_49_8",
      "type_flat": "TRec_49_8"
    },
    {
      "type": "TRec_49_9",
      "type_flat": "TRec_49_9"
    },
    {
      "type": "TRec_49_10",
      "type_flat": "TRec_49_10"
    },
    {
      "type": "TRec_50_1",
      "type_flat": "TRec_50_1"
    },
    {
      "type": "TRec_50_2",
      "type_flat": "TRec_50_2"
    },
    {
      "type": "TRec_50_3",
      "type_flat": "TRec_50_3"
    },
    {
      "type": "TRec_50_4",
      "type_flat": "TRec_50_4"
    },
    {
      "type": "TRec_50_5",
      "type_flat": "TRec_50_5"
    },
    {
      "type": "TRec_50_6",
      "type_flat": "TRec_50_6"
    },
    {
      "type": "TRec_50_7",
      "type_flat": "TRec_50_7"
    },
    {
      "type": "TRec_50_8",
      "type_flat": "TRec_50_8"
    },
    {
      "type": "TRec_50_9",
      "type_flat": "TRec_50_9"
    },
    {
      "type": "TRec_50_10",
      "type_flat": "TRec_50_10"
    }
  ]
}
